kan/__init__.py
kan/__main__.py
kan/__version__.py
kan/models.py
kan/structures.py
kan/tests/__init__.py
kan/tests/test_main.py
kan-0.0.2.dist-info/DESCRIPTION.rst
kan-0.0.2.dist-info/entry_points.txt
kan-0.0.2.dist-info/METADATA
kan-0.0.2.dist-info/metadata.json
kan-0.0.2.dist-info/RECORD
kan-0.0.2.dist-info/top_level.txt
kan-0.0.2.dist-info/WHEEL
