Metadata-Version: 2.0
Name: kan
Version: 0.0.2
Summary: 
